NekoYo/__init__.py
NekoYo/commands.py
NekoYo/serials.py
nekoyo-0.33.dist-info/licenses/LICENSE
nekoyo-0.33.dist-info/METADATA
nekoyo-0.33.dist-info/WHEEL
nekoyo-0.33.dist-info/entry_points.txt
nekoyo-0.33.dist-info/top_level.txt
nekoyo-0.33.dist-info/RECORD
