Metadata-Version: 2.4
Name: NekoYo
Version: 0.33
Summary: A Yaesu CAT commands library based on Python.
Home-page: https://github.com/GAQPanda/NekoYo
Author: FatPanda8885
Author-email: FatPanda8885@foxmail.com
License: Apache-2.0
Keywords: Yaesu CAT
Classifier: Development Status :: 3 - Alpha
Classifier: Intended Audience :: Developers
Classifier: Programming Language :: Python :: 3
Classifier: Programming Language :: Python :: 3.6
Classifier: Programming Language :: Python :: 3.7
Classifier: Programming Language :: Python :: 3.8
Classifier: Programming Language :: Python :: 3.9
Classifier: Programming Language :: Python :: 3.10
Classifier: Operating System :: OS Independent
License-File: LICENSE
Requires-Dist: pyserial
Dynamic: author
Dynamic: author-email
Dynamic: classifier
Dynamic: description
Dynamic: description-content-type
Dynamic: home-page
Dynamic: keywords
Dynamic: license
Dynamic: license-file
Dynamic: requires-dist
Dynamic: summary
